{
  "stats": {
    "suites": 1,
    "tests": 13,
    "passes": 13,
    "pending": 0,
    "failures": 0,
    "start": "2022-12-22T10:48:57.740Z",
    "end": "2022-12-22T10:49:02.066Z",
    "duration": 4222,
    "testsRegistered": 13,
    "passPercent": 100,
    "pendingPercent": 0,
    "other": 0,
    "hasOther": false,
    "skipped": 0,
    "hasSkipped": false
  },
  "results": [
    {
      "uuid": "dff4fe79-00e3-4460-bde1-433edfe0f47a",
      "title": "",
      "fullFile": "cypress/integration/jsGrowthTableDOM.spec.js",
      "file": "cypress/integration/jsGrowthTableDOM.spec.js",
      "beforeHooks": [],
      "afterHooks": [],
      "tests": [],
      "suites": [
        {
          "uuid": "02a59c22-8e77-4fca-8280-518371c5ab94",
          "title": "Table",
          "fullFile": "",
          "file": "",
          "beforeHooks": [],
          "afterHooks": [],
          "tests": [
            {
              "title": "should have 4 rows by default",
              "fullTitle": "Table should have 4 rows by default",
              "timedOut": null,
              "duration": 342,
              "state": "passed",
              "speed": "slow",
              "pass": true,
              "fail": false,
              "pending": false,
              "context": null,
              "code": "cy.get('@rows').should('have.length', 4);",
              "err": {},
              "uuid": "dc1131fb-0a9c-45f9-b4e0-444da5c80002",
              "parentUUID": "02a59c22-8e77-4fca-8280-518371c5ab94",
              "isHook": false,
              "skipped": false
            },
            {
              "title": "should add 1 row by click",
              "fullTitle": "Table should add 1 row by click",
              "timedOut": null,
              "duration": 249,
              "state": "passed",
              "speed": "slow",
              "pass": true,
              "fail": false,
              "pending": false,
              "context": null,
              "code": "cy.get('.append-row').click();\ncy.get('@rows').should('have.length', 5);",
              "err": {},
              "uuid": "303278bd-89e1-4947-84c9-78a571ac84e4",
              "parentUUID": "02a59c22-8e77-4fca-8280-518371c5ab94",
              "isHook": false,
              "skipped": false
            },
            {
              "title": "should have 4 columns by default",
              "fullTitle": "Table should have 4 columns by default",
              "timedOut": null,
              "duration": 116,
              "state": "passed",
              "speed": "slow",
              "pass": true,
              "fail": false,
              "pending": false,
              "context": null,
              "code": "cy.get('@columns').should('have.length', 4);",
              "err": {},
              "uuid": "d3b7f534-e9f9-467a-ba48-88048a3d66a8",
              "parentUUID": "02a59c22-8e77-4fca-8280-518371c5ab94",
              "isHook": false,
              "skipped": false
            },
            {
              "title": "should add 1 column by click",
              "fullTitle": "Table should add 1 column by click",
              "timedOut": null,
              "duration": 249,
              "state": "passed",
              "speed": "slow",
              "pass": true,
              "fail": false,
              "pending": false,
              "context": null,
              "code": "cy.get('.append-column').click();\ncy.get('@columns').should('have.length', 5);",
              "err": {},
              "uuid": "04647ca3-e1ac-4945-95c5-de1c0fb84000",
              "parentUUID": "02a59c22-8e77-4fca-8280-518371c5ab94",
              "isHook": false,
              "skipped": false
            },
            {
              "title": "should have max 10 columns",
              "fullTitle": "Table should have max 10 columns",
              "timedOut": null,
              "duration": 562,
              "state": "passed",
              "speed": "slow",
              "pass": true,
              "fail": false,
              "pending": false,
              "context": null,
              "code": "// 4 columns by default and click 7 times to add 7 columns\ncy.clickButton('.append-column', 7);\ncy.get('@columns').should('have.length', 10);",
              "err": {},
              "uuid": "ba9ee9a6-e5fb-49df-abe1-b3d43603905e",
              "parentUUID": "02a59c22-8e77-4fca-8280-518371c5ab94",
              "isHook": false,
              "skipped": false
            },
            {
              "title": "add column button should be disabled after 10 column",
              "fullTitle": "Table add column button should be disabled after 10 column",
              "timedOut": null,
              "duration": 457,
              "state": "passed",
              "speed": "slow",
              "pass": true,
              "fail": false,
              "pending": false,
              "context": null,
              "code": "// 4 columns by default and click 6 times to add 6 columns\ncy.clickButton('.append-column', 6);\ncy.get('.append-column').should('be.disabled');",
              "err": {},
              "uuid": "3600f333-1f7f-4879-b864-59c68fee3472",
              "parentUUID": "02a59c22-8e77-4fca-8280-518371c5ab94",
              "isHook": false,
              "skipped": false
            },
            {
              "title": "should remove one column",
              "fullTitle": "Table should remove one column",
              "timedOut": null,
              "duration": 179,
              "state": "passed",
              "speed": "slow",
              "pass": true,
              "fail": false,
              "pending": false,
              "context": null,
              "code": "cy.get('.remove-column').click();\ncy.get('@columns').should('have.length', 3);",
              "err": {},
              "uuid": "d690c911-8c35-4a79-80e3-2c267b75782b",
              "parentUUID": "02a59c22-8e77-4fca-8280-518371c5ab94",
              "isHook": false,
              "skipped": false
            },
            {
              "title": "should have max 10 rows",
              "fullTitle": "Table should have max 10 rows",
              "timedOut": null,
              "duration": 553,
              "state": "passed",
              "speed": "slow",
              "pass": true,
              "fail": false,
              "pending": false,
              "context": null,
              "code": "// 4 columns by default and click 7 times to add 7 rows\ncy.clickButton('.append-row', 7);\ncy.get('@rows').should('have.length', 10);",
              "err": {},
              "uuid": "24eb87ec-79aa-4433-adda-02b47fcd78eb",
              "parentUUID": "02a59c22-8e77-4fca-8280-518371c5ab94",
              "isHook": false,
              "skipped": false
            },
            {
              "title": "add row button should be disabled after 10 rows",
              "fullTitle": "Table add row button should be disabled after 10 rows",
              "timedOut": null,
              "duration": 442,
              "state": "passed",
              "speed": "slow",
              "pass": true,
              "fail": false,
              "pending": false,
              "context": null,
              "code": "// 4 columns by default and click 6 times to add 6 rows\ncy.clickButton('.append-row', 6);\ncy.get('.append-row').should('be.disabled');",
              "err": {},
              "uuid": "e02b1975-bf98-4a15-a440-602dd6ebf912",
              "parentUUID": "02a59c22-8e77-4fca-8280-518371c5ab94",
              "isHook": false,
              "skipped": false
            },
            {
              "title": "should remove one row",
              "fullTitle": "Table should remove one row",
              "timedOut": null,
              "duration": 176,
              "state": "passed",
              "speed": "slow",
              "pass": true,
              "fail": false,
              "pending": false,
              "context": null,
              "code": "cy.get('.remove-row').click();\ncy.get('@rows').should('have.length', 3);",
              "err": {},
              "uuid": "d91aae6f-9627-42e3-82b4-2db4fc78402d",
              "parentUUID": "02a59c22-8e77-4fca-8280-518371c5ab94",
              "isHook": false,
              "skipped": false
            },
            {
              "title": "should have 2 columns and 2 rows minimum",
              "fullTitle": "Table should have 2 columns and 2 rows minimum",
              "timedOut": null,
              "duration": 401,
              "state": "passed",
              "speed": "slow",
              "pass": true,
              "fail": false,
              "pending": false,
              "context": null,
              "code": "cy.get('.remove-row').click().click();\ncy.get('.remove-column').click().click();\ncy.get('@rows').should('have.length', 2);\ncy.get('@columns').should('have.length', 2);",
              "err": {},
              "uuid": "abf30ff2-e100-457f-9fec-f342ee931c10",
              "parentUUID": "02a59c22-8e77-4fca-8280-518371c5ab94",
              "isHook": false,
              "skipped": false
            },
            {
              "title": "remove row button should be disabled\n      when only 2 rows exist",
              "fullTitle": "Table remove row button should be disabled\n      when only 2 rows exist",
              "timedOut": null,
              "duration": 252,
              "state": "passed",
              "speed": "slow",
              "pass": true,
              "fail": false,
              "pending": false,
              "context": null,
              "code": "cy.get('.remove-row').click().click();\ncy.get('.remove-row').should('be.disabled');",
              "err": {},
              "uuid": "a75ccf34-8d15-40dc-aea9-b1b4bdcf5b96",
              "parentUUID": "02a59c22-8e77-4fca-8280-518371c5ab94",
              "isHook": false,
              "skipped": false
            },
            {
              "title": "remove column button should be disabled\n      when only 2 columns exist",
              "fullTitle": "Table remove column button should be disabled\n      when only 2 columns exist",
              "timedOut": null,
              "duration": 244,
              "state": "passed",
              "speed": "slow",
              "pass": true,
              "fail": false,
              "pending": false,
              "context": null,
              "code": "cy.get('.remove-column').click().click();\ncy.get('.remove-column').should('be.disabled');",
              "err": {},
              "uuid": "bca1b4f3-2ea6-4c3f-a629-362693d229cc",
              "parentUUID": "02a59c22-8e77-4fca-8280-518371c5ab94",
              "isHook": false,
              "skipped": false
            }
          ],
          "suites": [],
          "passes": [
            "dc1131fb-0a9c-45f9-b4e0-444da5c80002",
            "303278bd-89e1-4947-84c9-78a571ac84e4",
            "d3b7f534-e9f9-467a-ba48-88048a3d66a8",
            "04647ca3-e1ac-4945-95c5-de1c0fb84000",
            "ba9ee9a6-e5fb-49df-abe1-b3d43603905e",
            "3600f333-1f7f-4879-b864-59c68fee3472",
            "d690c911-8c35-4a79-80e3-2c267b75782b",
            "24eb87ec-79aa-4433-adda-02b47fcd78eb",
            "e02b1975-bf98-4a15-a440-602dd6ebf912",
            "d91aae6f-9627-42e3-82b4-2db4fc78402d",
            "abf30ff2-e100-457f-9fec-f342ee931c10",
            "a75ccf34-8d15-40dc-aea9-b1b4bdcf5b96",
            "bca1b4f3-2ea6-4c3f-a629-362693d229cc"
          ],
          "failures": [],
          "pending": [],
          "skipped": [],
          "duration": 4222,
          "root": false,
          "rootEmpty": false,
          "_timeout": 2000
        }
      ],
      "passes": [],
      "failures": [],
      "pending": [],
      "skipped": [],
      "duration": 0,
      "root": true,
      "rootEmpty": true,
      "_timeout": 2000
    }
  ],
  "meta": {
    "mocha": {
      "version": "7.0.1"
    },
    "mochawesome": {
      "options": {
        "quiet": false,
        "reportFilename": "mochawesome",
        "saveHtml": false,
        "saveJson": true,
        "consoleReporter": "spec",
        "useInlineDiffs": false,
        "code": true
      },
      "version": "6.2.1"
    },
    "marge": {
      "options": {
        "reportDir": "raw_reports",
        "overwrite": false,
        "html": false,
        "json": true
      },
      "version": "5.1.0"
    }
  }
}